MANIFEST.in
README.txt
setup.cfg
setup.py
beyondskins/__init__.py
beyondskins.ploneday.site2011.egg-info/PKG-INFO
beyondskins.ploneday.site2011.egg-info/SOURCES.txt
beyondskins.ploneday.site2011.egg-info/dependency_links.txt
beyondskins.ploneday.site2011.egg-info/entry_points.txt
beyondskins.ploneday.site2011.egg-info/namespace_packages.txt
beyondskins.ploneday.site2011.egg-info/not-zip-safe
beyondskins.ploneday.site2011.egg-info/requires.txt
beyondskins.ploneday.site2011.egg-info/top_level.txt
beyondskins/ploneday/__init__.py
beyondskins/ploneday/site2011/README.txt
beyondskins/ploneday/site2011/__init__.py
beyondskins/ploneday/site2011/config.py
beyondskins/ploneday/site2011/configure.zcml
beyondskins/ploneday/site2011/tests.py
beyondskins/ploneday/site2011/version.txt
beyondskins/ploneday/site2011/browser/__init__.py
beyondskins/ploneday/site2011/browser/configure.zcml
beyondskins/ploneday/site2011/browser/interfaces.py
beyondskins/ploneday/site2011/browser/images/README.txt
beyondskins/ploneday/site2011/browser/stylesheets/README.txt
beyondskins/ploneday/site2011/browser/templates/footer.pt
beyondskins/ploneday/site2011/docs/__init__.py
beyondskins/ploneday/site2011/docs/browser.txt
beyondskins/ploneday/site2011/docs/screenshot.jpg
beyondskins/ploneday/site2011/docs/wpd-logo.psd
beyondskins/ploneday/site2011/profiles/default/beyondskins.ploneday.site2011.txt
beyondskins/ploneday/site2011/profiles/default/browserlayer.xml
beyondskins/ploneday/site2011/profiles/default/cssregistry.xml
beyondskins/ploneday/site2011/profiles/default/metadata.xml
beyondskins/ploneday/site2011/profiles/default/skins.xml
beyondskins/ploneday/site2011/profiles/default/viewlets.xml
beyondskins/ploneday/site2011/profiles/uninstall/beyondskins.ploneday.site2011.txt
beyondskins/ploneday/site2011/profiles/uninstall/cssregistry.xml
beyondskins/ploneday/site2011/profiles/uninstall/skins.xml
beyondskins/ploneday/site2011/profiles/uninstall/viewlets.xml
beyondskins/ploneday/site2011/skins/ploneday_images/bg.png
beyondskins/ploneday/site2011/skins/ploneday_images/logo-footer-simples.png
beyondskins/ploneday/site2011/skins/ploneday_images/logo-footer.png
beyondskins/ploneday/site2011/skins/ploneday_images/wpd-logo.png
beyondskins/ploneday/site2011/skins/ploneday_images/wpd-logo.png.metadata
beyondskins/ploneday/site2011/skins/ploneday_styles/base_properties.props
