Metadata-Version: 1.0
Name: beyondskins.ploneday.site2011
Version: 1.0
Summary: World Plone Day 2011 theme.
Home-page: http://www.simplesconsultoria.com.br/
Author: Simples Consultoria
Author-email: products@simplesconsultoria.com.br
License: GPL
Keywords: web zope plone theme skin simples_consultoria
Platform: UNKNOWN
Classifier: Framework :: Plone
Classifier: Framework :: Zope2
Classifier: Framework :: Zope3
Classifier: Programming Language :: Python
Classifier: Topic :: Software Development :: Libraries :: Python Modules
